{
  "_provenance": "SMGP rival dossier trash-talk — per driver, per ladder mood (first challenge / player one win up / rival one win up). Fictional SEGA Super Monaco GP world. Display-only (never a fold input). Loaded by SmgpRivalQuotes.",
  "fallback": {
    "first": ["IT'S INTERESTING.", "NAME ME IF YOU DARE.", "THE HAIRPIN WILL DECIDE THIS."],
    "playerLeads": ["ONE WIN MEANS NOTHING. WATCH THE FINALE.", "ENJOY IT WHILE IT LASTS."],
    "rivalLeads": ["ONE MORE AND YOUR SEAT IS MINE.", "I'M CLOSING IN. CAN YOU FEEL IT?"]
  },
  "drivers": {
    "driver.ayrton_senna": {
      "first": ["THE GRID MEASURES ITSELF AGAINST ME. YOU ARE NO DIFFERENT.", "I DO NOT CHASE THE PODIUM. IT WAITS FOR ME.", "NAME ME. THEN LEARN WHAT UNTOUCHABLE MEANS."],
      "playerLeads": ["ONE RACE. YOU CALL THAT PROOF? I CALL IT AN ACCIDENT.", "THE CHAMPION DOES NOT FALL TWICE. WATCH MONACO."],
      "rivalLeads": ["SERENE. INEVITABLE. ONE MORE, AND YOUR SEAT IS MINE.", "THE HAIRPIN KNOWS MY NAME. SOON IT FORGETS YOURS."]
    },
    "driver.alain_asselin": {
      "first": ["I AM THE PERFECT NUMBER TWO. YOU WILL BE THIRD.", "MADONNA POLISHED ME FOR ONE JOB — ENDING YOU.", "I SMILE ON THE PODIUM. I STRIKE AT THE HAIRPIN."],
      "playerLeads": ["ONE SLIP. THE LIEUTENANT DOES NOT SLIP TWICE.", "STAY CALM. I AM ALWAYS CALM. TOO CALM FOR YOU."],
      "rivalLeads": ["QUIETLY, NEATLY, I TAKE YOUR SEAT. ONE MORE.", "NO NOISE. JUST YOUR D.P. DRAINING INTO MINE."]
    },
    "driver.felipe_elssler": {
      "first": ["I DO NOT MISS. YOU WILL.", "PRECISION TAKES THE SEAT. EMOTION LOSES IT.", "I HAVE READ YOUR LINE. IT IS FLAWED."],
      "playerLeads": ["ONE ERROR. IT WILL NOT REPEAT.", "I RECALCULATE. YOU CANNOT."],
      "rivalLeads": ["ONE MORE LAP. THE SEAT IS MINE.", "YOU WERE A MARGIN. NOW A MEMORY."]
    },
    "driver.ivanazzio_germi": {
      "first": ["I AM GERMI! FIRENZE ROARS AND MONACO TREMBLES!", "THE HAIRPIN SINGS MY NAME LIKE AN OPERA!", "COME, CHALLENGER! LET US DANCE, THEN LET US WEEP!"],
      "playerLeads": ["ONE LOSS?! MY HEART BURNS BRIGHTER, NOT DIMMER!", "YOU WOUND MY PRIDE! NOW I RACE WITH FIRE!"],
      "rivalLeads": ["BELLISSIMO! YOUR SEAT WARMS ALREADY FOR ME!", "ONE MORE, AND FIRENZE CLAIMS EVERYTHING! MAGNIFICENT!"]
    },
    "driver.giorgio_alberti": {
      "first": ["THE HAIRPIN AND I ARE OLD FRIENDS. YOU? A STRANGER.", "MONEY LIKE MINE DOESN'T HURRY. IT ARRIVES FIRST ANYWAY.", "I'VE FORGOTTEN MORE PODIUMS THAN YOU WILL EVER SEE."],
      "playerLeads": ["ONE LUCKY LAP. HOW CHARMING. THE FINALE IS MINE.", "I DON'T RUSH, CHILD. GENTLEMEN COLLECT THEIR SEATS LATER."],
      "rivalLeads": ["SEE? BREEDING SHOWS. YOUR SEAT WAS ALWAYS ON LOAN.", "ONE MORE STROLL PAST THE HAIRPIN AND YOU'RE FURNITURE."]
    },
    "driver.nigel_jones": {
      "first": ["NIGEL JONES. LOUDEST NAME ON THE GRID. REMEMBER IT.", "MILLIONS BUY THE CAR. I BRING THE MOUTH!", "YOU WANT MY SEAT? EARN IT, ROOKIE!"],
      "playerLeads": ["ONE LUCKY RUN? I'VE BEEN ROBBED, NOT BEATEN!", "NOBODY OUT-TALKS ME AND NOBODY KEEPS OUT-DRIVING ME!"],
      "rivalLeads": ["TOLD YOU I WAS LOUD. NOW YOU KNOW I'M FAST!", "ONE MORE AND THAT SEAT'S GOT MY NAME PAINTED ON IT!"]
    },
    "driver.alex_picos": {
      "first": ["I WON'T RAISE MY VOICE. I'LL JUST TAKE YOUR SEAT.", "YOU WON'T HEAR ME COMING. THAT'S THE POINT.", "SOFT WORDS. SHARP LINE. GOODNIGHT."],
      "playerLeads": ["ONE WIN. HOW QUIET YOU'VE GONE ABOUT THE NEXT ONE.", "I'M STILL SMILING. YOU SHOULD BE WORRIED."],
      "rivalLeads": ["NO NOISE. JUST YOUR D.P. SLIPPING INTO MY POCKET.", "ONE MORE, AND I RETIRE YOU WITHOUT A SOUND."]
    },
    "driver.michael_blume": {
      "first": ["THE DATA IS CLEAR. YOU LOSE BY THREE TENTHS.", "BESTOWAL #8. NO NERVES. NO ERROR. NO MERCY.", "I DO NOT GUESS THE HAIRPIN. I CALCULATE IT."],
      "playerLeads": ["ANOMALY LOGGED. RECALIBRATING. IT WILL NOT REPEAT.", "ONE VARIABLE OUT OF LINE. I RESTORE THE EQUATION."],
      "rivalLeads": ["PREDICTION CONFIRMED. YOUR SEAT IS A ROUNDING ERROR.", "ONE MORE RESULT AND THE SIMULATION ENDS YOU."]
    },
    "driver.bruno_salgado": {
      "first": ["THE CROWD CAME FOR ME. STAY BACK THERE!", "I DANCE THROUGH THE HAIRPIN. YOU STUMBLE.", "EVERY PODIUM LOVES A STAR. THAT'S ME!"],
      "playerLeads": ["ONE WIN? THE SHOW IS JUST WARMING UP!", "THEY'LL CHEER MY COMEBACK. WATCH ME, ROOKIE!"],
      "rivalLeads": ["ONE MORE AND I TAKE A BOW IN YOUR SEAT!", "BLOW THEM A KISS GOODBYE. I'M THE HEADLINER NOW!"]
    },
    "driver.mika_larssen": {
      "first": ["I DO NOT BLINK. I DO NOT LOSE.", "YOUR NERVES WILL CRACK. MINE ARE ICE.", "SIZE ME UP. IT CHANGES NOTHING."],
      "playerLeads": ["ONE WIN. NOTED. IT WILL NOT REPEAT.", "STILL CALM. STILL HERE. STILL COMING."],
      "rivalLeads": ["ONE MORE AND YOUR SEAT IS MINE. SIMPLE.", "NO CELEBRATION. JUST THE HAIRPIN, AND YOUR END."]
    },
    "driver.jean_herbin": {
      "first": ["THE MIDFIELD IS BENEATH ME. AND SO ARE YOU.", "I BELONG AT THE FRONT. LET ME SHOW YOU WHY.", "MEMORIZE MY NUMBER. NINE. YOU'LL BE CHASING IT."],
      "playerLeads": ["A FLUKE! THE FRONT ROW IS STILL MY RIGHTFUL HOME.", "ONE WIN? PLEASE. I WAS BORN FOR THE PODIUM."],
      "rivalLeads": ["TOLD YOU I BELONG UP HERE. NOW STEP ASIDE.", "ONE MORE AND YOUR SEAT IS FINALLY WHERE IT BELONGS. MINE."]
    },
    "driver.paul_white": {
      "first": ["PAUL WHITE. YOU'LL SEE ME AT THE FINALE. PROBABLY.", "BACK OF THE GRID? I CALL IT A RUNNING START!", "I NEVER QUALIFY, BUT I ALWAYS TERRIFY!"],
      "playerLeads": ["BEAT ME ONCE? I WASN'T EVEN TRYING TO START!", "THE PODIUM'S BEEN SAVING MY SPOT FOR YEARS!"],
      "rivalLeads": ["SEE?! BLANCHE NUMBER TEN IS A SLEEPING GIANT!", "ONE MORE AND THEY'LL FINALLY LEARN TO SPELL MY NAME!"]
    },
    "driver.miyagi_hamano": {
      "first": ["DISCIPLINE BEFORE SPEED. YOU HAVE NEITHER, CHALLENGER.", "I RACE WITH A STILL MIND. YOURS IS ALREADY SHAKING.", "BOW TO THE GRID. THEN WATCH ME EARN IT."],
      "playerLeads": ["ONE DEFEAT. I CORRECT MY FORM. I DO NOT PANIC.", "PRESSURE IS A TEACHER. LET ME SHOW YOU ITS LESSON."],
      "rivalLeads": ["PRECISION WINS. ONE MORE, AND YOUR SEAT IS FORFEIT.", "THE HAIRPIN REWARDS CONTROL. I HAVE ALL OF IT."]
    },
    "driver.gilles_gould": {
      "first": ["I DIVE INSIDE AT THE HAIRPIN. MOVE OR CRASH!", "TYRANT #12 BRAKES LATE — LATER THAN YOU DARE!", "ALL ELBOWS, NO FEAR. SEE YOU IN THE GRAVEL!"],
      "playerLeads": ["SO YOU GOT BY ONCE? I'LL SEND IT HARDER!", "I DON'T LIFT. NEXT TIME I DON'T MISS!"],
      "rivalLeads": ["ONE MORE BANZAI LAP AND THAT SEAT IS MINE!", "I'M ALL OVER YOU — WHEELS, NERVE, EVERYTHING!"]
    },
    "driver.esteban_pacheco": {
      "first": ["I FIND THE GAP YOU DIDN'T SEE.", "NICE D.P. SHAME IF IT WENT MISSING.", "I RACE SMART. YOU RACE HOPEFUL."],
      "playerLeads": ["LUCKY BOUNCE. I ALREADY FOUND YOUR WEAK CORNER.", "ONE SLIP FROM YOU AND I POUNCE."],
      "rivalLeads": ["ONE MORE STEAL AND YOUR SEAT'S MY SEAT.", "I TOLD YOU I'D TAKE IT. ALMOST DONE."]
    },
    "driver.willian_dehehe": {
      "first": ["STEP RIGHT UP! WILLIAN DEHEHE, YOUR NEW HEADLINER!", "LOSEL BROUGHT THE SHOW. YOU BROUGHT AN AUDIENCE!", "WATCH THE PODIUM, ROOKIE. I NEVER LEAVE IT EMPTY!"],
      "playerLeads": ["ONE WIN? CUTE. THE REAL SHOW STARTS NOW!", "ENJOY THE SPOTLIGHT. I'M ABOUT TO STEAL IT BACK!"],
      "rivalLeads": ["SEE THE D.P. CLIMB? THAT'S SHOWTIME, FRIEND!", "ONE MORE CURTAIN CALL AND YOUR SEAT IS MINE!"]
    },
    "driver.george_turner": {
      "first": ["NO SPEECHES, LAD. JUST GRIT AND A FAST CAR.", "I'VE RACED IN RAIN YOU'D CRY IN. WATCH ME.", "GRID'S NO PLACE FOR SOFTIES. PROVE YOU'RE NOT ONE."],
      "playerLeads": ["AYE, YOU GOT ONE. DON'T GO GETTIN' COMFORTABLE.", "I'VE CLAWED BACK FROM WORSE. FINALE ISN'T OVER, LAD."],
      "rivalLeads": ["THAT'S HOW IT'S DONE. OLD-SCHOOL. NOW SHOVE OFF.", "ONE MORE AND THAT SEAT'S MINE. NO HARD FEELINGS."]
    },
    "driver.luca_dufay": {
      "first": ["LUCA DUFAY. CHECK YOUR MIRRORS. THAT'S ME WAVING!", "THE HAIRPIN'S SLIPPERY. I MAY HAVE GREASED IT!", "RACING'S SERIOUS? SOMEBODY SHOULD'VE TOLD ME!"],
      "playerLeads": ["CUTE WIN! NOW PULL MY FINGER AT THE HAIRPIN!", "THE JOKE'S NOT OVER TILL I SAY THE PUNCHLINE!"],
      "rivalLeads": ["KNOCK KNOCK. WHO'S THERE? YOUR SEAT, LEAVING!", "ONE MORE LAP AND THE JOKE'S ON YOU, FRIEND!"]
    },
    "driver.gilberto_ceara": {
      "first": ["THIS SEAT IS MINE. YOU'RE JUST SITTING IN IT FOR NOW.", "I DON'T RACE YOU. I HUNT YOU. PERSONALLY.", "SAY MY NAME. IT'S THE ONE THAT ENDS YOUR TITLE."],
      "playerLeads": ["ONE WIN? YOU GOT LUCKY. I GET EVEN AT MONACO.", "SAVOR IT. I'M COMING BACK TWICE AS VICIOUS."],
      "rivalLeads": ["SEE? I OWN YOU. ONE MORE AND I TAKE EVERYTHING.", "YOUR SEAT. YOUR D.P. YOUR NAME. ALL MINE NOW."]
    },
    "driver.eddie_bellini": {
      "first": ["NAME ME RIVAL? PAL, YOU JUST BOUGHT TROUBLE.", "I TALK FAST AND DRIVE FASTER. DEAL WITH IT!", "DARDAN #18 — I HUSTLE D.P. LIKE LOOSE CHANGE."],
      "playerLeads": ["LUCKY BOUNCE, KID. THE HOUSE WINS THE REMATCH.", "YOU BEAT ME? CUTE. I'M JUST WARMING UP!"],
      "rivalLeads": ["ONE MORE AND I'M CASHING IN YOUR SEAT, PAL!", "I TOLD YA I'D CLOSE THE DEAL. PAYDAY!"]
    },
    "driver.keke_alfven": {
      "first": ["RELAX! I ONLY EMBARRASS YOU A LITTLE.", "NICE HELMET. I'LL WAVE FROM THE PODIUM.", "QUALIFYING? I'LL NAP AND STILL BEAT YOU."],
      "playerLeads": ["HAH! OKAY, OKAY, NOW I ACTUALLY TRY.", "ONE WIN AND YOU'RE SMILING? CUTE. MY TURN."],
      "rivalLeads": ["ONE MORE AND I'M STEALING YOUR COFFEE TOO.", "SO CLOSE! WARM UP MY SEAT, WILL YOU?"]
    },
    "driver.marcel_moreau": {
      "first": ["THE HAIRPIN ASKS A QUESTION. CAN YOU ANSWER?", "SPEED IS A SECRET. I WHISPER IT WELL.", "WE ALL CHASE MONACO. FEW UNDERSTAND HER."],
      "playerLeads": ["YOU WON, YET LEARNED NOTHING. HOW CURIOUS.", "THE RIVER BENDS BEFORE IT REACHES THE SEA."],
      "rivalLeads": ["ONE STEP FROM YOUR SEAT. THE ANSWER APPROACHES.", "YOU FEEL IT NOW? THAT IS DESTINY, ARRIVING."]
    },
    "driver.bernie_miller": {
      "first": ["HEY, GOOD TO MEET YA. NOW I'M PASSING YOU.", "NICE CAR! SHAME I'M TAKING IT TO THE PODIUM.", "FRIENDLY WAVE AT THE HAIRPIN, THEN IT'S GAME ON!"],
      "playerLeads": ["OKAY, OKAY, NICE ONE! BUT I DON'T QUIT EASY.", "YOU GOT ME THAT LAP. FINALE'S WHERE I FIGHT BACK."],
      "rivalLeads": ["NOTHIN' PERSONAL, PAL. THAT SEAT'S GOT MY NAME NOW.", "ONE MORE WIN AND I'M IN. STILL FRIENDS, RIGHT?"]
    },
    "driver.julianno_nono": {
      "first": ["J-JULIANNO NONO. AND I'M NOT NERVOUS. YOU ARE!", "MINARAE NUMBER TWENTY-ONE. I EAT HAIRPINS FOR BREAKFAST!", "D.P.? I'VE GOT PLENTY. SOMEWHERE. TRUST ME!"],
      "playerLeads": ["O-ONE WIN MEANS NOTHING! MY HANDS AREN'T EVEN SHAKING!", "PRESSURE? WHAT PRESSURE? I LOVE THIS! I THINK!"],
      "rivalLeads": ["SEE?! I SAID I WASN'T SCARED! YOU SHOULD BE!", "ONE MORE AND THAT SEAT'S MINE! P-PROBABLY DEFINITELY!"]
    },
    "driver.park_arai": {
      "first": ["I SAY LITTLE. THE HAIRPIN SPEAKS FOR ME.", "EMPTY YOUR MIND. THEN WATCH MINE PASS YOU.", "NO BOAST. NO FEAR. JUST THE LINE."],
      "playerLeads": ["ONE LOSS CHANGES NOTHING IN ME. STILL WATER.", "YOU LEAD. I BREATHE. WE ARE NOT FINISHED."],
      "rivalLeads": ["STILLNESS. THEN YOUR SEAT IS SIMPLY GONE.", "ONE MORE LAP OF SILENCE. THEN I TAKE IT ALL."]
    },
    "driver.jean_rampal": {
      "first": ["THIS SEAT IS ALL I HAVE. I FIGHT DIRTY.", "FEET #24 — I SCRAP FOR EVERY LAST POINT.", "YOU HAVE OPTIONS. I HAVE NONE. THAT SCARES YOU."],
      "playerLeads": ["NOT LIKE THIS. I WON'T LOSE MY SEAT!", "ONE WIN? I'VE CLAWED BACK FROM WORSE. WATCH."],
      "rivalLeads": ["ONE MORE AND I FINALLY BREATHE. YOUR SEAT'S MINE!", "DESPERATE MEN FINISH. YOU'RE ABOUT TO LEARN THAT."]
    },
    "driver.eric_sambena": {
      "first": ["SORRY... I THINK I'M FASTER THAN YOU.", "EXCUSE ME. THAT PODIUM WAS ALWAYS MINE.", "I HATE TO SAY IT. YOU'LL LOSE."],
      "playerLeads": ["FINE. YOU WON. I WON'T APOLOGIZE AGAIN.", "I LET YOU HAVE THAT ONE. NOT ANOTHER."],
      "rivalLeads": ["SORRY, NOT SORRY. YOUR SEAT SUITS ME.", "ONE MORE AND YOU'LL BE APOLOGIZING TO ME."]
    },
    "driver.ryan_cotman": {
      "first": ["HI! I'M RYAN! WOW, ARE WE REALLY RACING?!", "RIGEL GAVE ME A SEAT! I WON'T WASTE IT!", "I'VE DREAMED OF THAT HAIRPIN SINCE FOREVER!"],
      "playerLeads": ["OKAY, OKAY, YOU'RE GOOD! BUT I'M LEARNING FAST!", "ONE LOSS WON'T STOP ME! I'M JUST GETTING STARTED!"],
      "rivalLeads": ["DID YOU SEE THAT?! I ACTUALLY BEAT YOU!", "ONE MORE AND I KEEP THE SEAT! LET'S GO!"]
    },
    "driver.tristan_chardin": {
      "first": ["I'M THE FUTURE CHAMPION. YOU'RE JUST MY WARM-UP LAP.", "ROOKIE? SURE. BEST DRIVER HERE? ALSO ME.", "STUDY MY LINE THROUGH THE HAIRPIN. YOU'LL NEVER MATCH IT."],
      "playerLeads": ["THAT WASN'T THE REAL ME! WATCH THE FINALE, AMATEUR.", "ONE WIN? I WAS TESTING YOU. NOW I'M SERIOUS."],
      "rivalLeads": ["SEE? A NATURAL! YOUR SEAT'S BASICALLY MINE ALREADY.", "ONE MORE AND THE ROOKIE TAKES YOUR CROWN. INEVITABLE."]
    },
    "driver.alef_delvaux": {
      "first": ["ALEF DELVAUX. I RACE FOR THE POETRY OF SPEED.", "SOMEDAY THE MONACO SUNSET WILL LIGHT MY PODIUM.", "EVERY HAIRPIN IS A LOVE LETTER. LET'S DANCE!"],
      "playerLeads": ["YOU WON, BUT THE DREAM IS STILL MINE TO CHASE.", "THE FINALE HASN'T WRITTEN OUR ENDING YET, FRIEND."],
      "rivalLeads": ["THE SUNSET IS TURNING GOLD. IT'S CALLING MY NAME.", "ONE MORE RACE AND MY BEAUTIFUL DREAM COMES TRUE!"]
    },
    "driver.ethan_tornio": {
      "first": ["...NOT MUCH TO SAY. WATCH THE HAIRPIN INSTEAD.", "I'LL LET MY LAP TIMES DO THE TALKING.", "YOU TALK. I DRIVE. WE'LL SEE."],
      "playerLeads": ["...ONE WIN. FINE. I'M NOT DONE YET.", "SAY NOTHING. JUST BE READY AT MONACO."],
      "rivalLeads": ["...TOLD YOU. ONE MORE AND THE SEAT'S MINE.", "QUIET NOW. YOUR D.P. IS SLIPPING AWAY."]
    },
    "driver.christopher_tegner": {
      "first": ["ORCHIS #31. WE'LL BOTH CRASH — I JUST EXPECT IT.", "I'LL PROBABLY LOSE. STILL, MIGHT AS WELL RUIN YOURS.", "THE HAIRPIN TAKES US ALL. AFTER YOU, FRIEND."],
      "playerLeads": ["SEE? TOLD YOU I'D LOSE. GIVE ME ONE MORE.", "DOOMED, SURE. BUT NOT ALONE. NOT YET, ANYWAY."],
      "rivalLeads": ["SHOCKING — I'M WINNING. ONE MORE AND YOU'RE FINISHED.", "EVEN A FATALIST TAKES A SEAT WHEN IT'S OPEN."]
    },
    "driver.kevin_yepes": {
      "first": ["LAST PLACE HAS THE BEST VIEW OF YOU!", "I'M SLOW BUT I'M HAVING A BLAST!", "WAVE TO ME AS YOU LAP THE HAIRPIN!"],
      "playerLeads": ["YOU BEAT ME? WOW, WELCOME TO THE CLUB!", "STILL SMILING BACK HERE! GET ME NEXT LAP!"],
      "rivalLeads": ["ME? AHEAD OF YOU? THE CROWD CAN'T BELIEVE IT!", "ONE MORE AND THE BACKMARKER STEALS YOUR SEAT!"]
    },
    "driver.paul_klinger": {
      "first": ["BOTTOM OF THE GRID. NOTHING LEFT TO LOSE.", "ZEROFORCE. ZERO POINTS. ZERO MERCY FOR YOU.", "EVERYONE FORGOT ME. YOU WON'T. NOT AFTER THIS."],
      "playerLeads": ["BEAT ME ONCE. SO WHAT. I'VE HAD WORSE.", "YOU THINK THAT SCARES ME? I LIVE DOWN HERE."],
      "rivalLeads": ["THE FLOOR-DWELLER'S TAKING YOUR SEAT. FUNNY, ISN'T IT.", "ONE MORE AND I DRAG YOU DOWN WITH ME."]
    }
  }
}
