{"year":2018,"source":"Derived from the f1db dataset (CC BY 4.0) — https://github.com/f1db/f1db","driversChampion":{"driver":"Lewis Hamilton","team":"Mercedes","points":"408"},"constructorsChampion":{"team":"Mercedes","points":"655"},"runnerUp":{"driver":"Sebastian Vettel","points":"320"},"rounds":[{"round":1,"name":"Australian Grand Prix","winner":"Sebastian Vettel","winnerTeam":"Ferrari","fastestLap":"Daniel Ricciardo","circuit":{"layoutId":"melbourne-1","name":"Melbourne","place":"Melbourne","type":"STREET","direction":"CLOCKWISE","lengthKm":"5.3","turns":16,"history":"The Melbourne circuit (formerly Albert Park Circuit) hosted 22 F1 World Championship Grands Prix between 1996 and 2017.","facts":["First Grand Prix here: 1996 — 22 World Championship GPs held coming into this season.","Most wins here: Michael Schumacher (4).","Most pole positions: Lewis Hamilton (6).","Most successful constructor: Ferrari (7 wins).","12 different winners in 22 Grands Prix.","Race lap record on this layout: 1:24.125 — Michael Schumacher (2004)."]},"results":[{"pos":"1","driver":"Sebastian Vettel","team":"Ferrari"},{"pos":"2","driver":"Lewis Hamilton","team":"Mercedes"},{"pos":"3","driver":"Kimi Räikkönen","team":"Ferrari"},{"pos":"4","driver":"Daniel Ricciardo","team":"Red Bull"},{"pos":"5","driver":"Fernando Alonso","team":"McLaren"},{"pos":"6","driver":"Max Verstappen","team":"Red Bull"},{"pos":"7","driver":"Nico Hülkenberg","team":"Renault"},{"pos":"8","driver":"Valtteri Bottas","team":"Mercedes"},{"pos":"9","driver":"Stoffel Vandoorne","team":"McLaren"},{"pos":"10","driver":"Carlos Sainz Jr.","team":"Renault"},{"pos":"11","driver":"Sergio Pérez","team":"Force India"},{"pos":"12","driver":"Esteban Ocon","team":"Force India"},{"pos":"13","driver":"Charles Leclerc","team":"Sauber"},{"pos":"14","driver":"Lance Stroll","team":"Williams"},{"pos":"15","driver":"Brendon Hartley","team":"Toro Rosso"},{"pos":"DNF","driver":"Romain Grosjean","team":"Haas","status":"Wheel"},{"pos":"DNF","driver":"Kevin Magnussen","team":"Haas","status":"Wheel"},{"pos":"DNF","driver":"Pierre Gasly","team":"Toro Rosso","status":"Engine"},{"pos":"DNF","driver":"Marcus Ericsson","team":"Sauber","status":"Hydraulics"},{"pos":"DNF","driver":"Sergey Sirotkin","team":"Williams","status":"Brakes"}]},{"round":2,"name":"Bahrain Grand Prix","winner":"Sebastian Vettel","winnerTeam":"Ferrari","fastestLap":"Valtteri Bottas","circuit":{"layoutId":"bahrain-1","name":"Bahrain","place":"Sakhir","type":"RACE","direction":"CLOCKWISE","lengthKm":"5.41","turns":15,"history":"The Bahrain circuit in Sakhir hosted 13 F1 World Championship Grands Prix between 2004 and 2017.","facts":["First Grand Prix here: 2004 — 13 World Championship GPs held coming into this season.","Most wins here: Fernando Alonso / Sebastian Vettel (3 each).","Most pole positions: Lewis Hamilton / Michael Schumacher / Nico Rosberg / Sebastian Vettel (2 each).","Most successful constructor: Ferrari (5 wins).","7 different winners in 13 Grands Prix.","Race lap record on this layout: 1:30.252 — Michael Schumacher (2004)."]},"results":[{"pos":"1","driver":"Sebastian Vettel","team":"Ferrari"},{"pos":"2","driver":"Valtteri Bottas","team":"Mercedes"},{"pos":"3","driver":"Lewis Hamilton","team":"Mercedes"},{"pos":"4","driver":"Pierre Gasly","team":"Toro Rosso"},{"pos":"5","driver":"Kevin Magnussen","team":"Haas"},{"pos":"6","driver":"Nico Hülkenberg","team":"Renault"},{"pos":"7","driver":"Fernando Alonso","team":"McLaren"},{"pos":"8","driver":"Stoffel Vandoorne","team":"McLaren"},{"pos":"9","driver":"Marcus Ericsson","team":"Sauber"},{"pos":"10","driver":"Esteban Ocon","team":"Force India"},{"pos":"11","driver":"Carlos Sainz Jr.","team":"Renault"},{"pos":"12","driver":"Charles Leclerc","team":"Sauber"},{"pos":"13","driver":"Romain Grosjean","team":"Haas"},{"pos":"14","driver":"Lance Stroll","team":"Williams"},{"pos":"15","driver":"Sergey Sirotkin","team":"Williams"},{"pos":"16","driver":"Sergio Pérez","team":"Force India"},{"pos":"17","driver":"Brendon Hartley","team":"Toro Rosso"},{"pos":"DNF","driver":"Kimi Räikkönen","team":"Ferrari","status":"Wheel"},{"pos":"DNF","driver":"Max Verstappen","team":"Red Bull","status":"Transmission"},{"pos":"DNF","driver":"Daniel Ricciardo","team":"Red Bull","status":"Electrical"}]},{"round":3,"name":"Chinese Grand Prix","winner":"Daniel Ricciardo","winnerTeam":"Red Bull","fastestLap":"Daniel Ricciardo","circuit":{"layoutId":"shanghai-1","name":"Shanghai","place":"Shanghai","type":"RACE","direction":"CLOCKWISE","lengthKm":"5.45","turns":16,"history":"The Shanghai circuit hosted 14 F1 World Championship Grands Prix between 2004 and 2017.","facts":["First Grand Prix here: 2004 — 14 World Championship GPs held coming into this season.","Most wins here: Lewis Hamilton (5).","Most pole positions: Lewis Hamilton (6).","Most successful constructor: Mercedes (5 wins).","8 different winners in 14 Grands Prix.","Race lap record on this layout: 1:32.238 — Michael Schumacher (2004)."]},"results":[{"pos":"1","driver":"Daniel Ricciardo","team":"Red Bull"},{"pos":"2","driver":"Valtteri Bottas","team":"Mercedes"},{"pos":"3","driver":"Kimi Räikkönen","team":"Ferrari"},{"pos":"4","driver":"Lewis Hamilton","team":"Mercedes"},{"pos":"5","driver":"Max Verstappen","team":"Red Bull"},{"pos":"6","driver":"Nico Hülkenberg","team":"Renault"},{"pos":"7","driver":"Fernando Alonso","team":"McLaren"},{"pos":"8","driver":"Sebastian Vettel","team":"Ferrari"},{"pos":"9","driver":"Carlos Sainz Jr.","team":"Renault"},{"pos":"10","driver":"Kevin Magnussen","team":"Haas"},{"pos":"11","driver":"Esteban Ocon","team":"Force India"},{"pos":"12","driver":"Sergio Pérez","team":"Force India"},{"pos":"13","driver":"Stoffel Vandoorne","team":"McLaren"},{"pos":"14","driver":"Lance Stroll","team":"Williams"},{"pos":"15","driver":"Sergey Sirotkin","team":"Williams"},{"pos":"16","driver":"Marcus Ericsson","team":"Sauber"},{"pos":"17","driver":"Romain Grosjean","team":"Haas"},{"pos":"18","driver":"Pierre Gasly","team":"Toro Rosso"},{"pos":"19","driver":"Charles Leclerc","team":"Sauber"},{"pos":"20","driver":"Brendon Hartley","team":"Toro Rosso","status":"Gearbox"}]},{"round":4,"name":"Azerbaijan Grand Prix","winner":"Lewis Hamilton","winnerTeam":"Mercedes","fastestLap":"Valtteri Bottas","circuit":{"layoutId":"baku-1","name":"Baku","place":"Baku","type":"STREET","direction":"ANTI_CLOCKWISE","lengthKm":"6","turns":20,"history":"The Baku circuit hosted 2 F1 World Championship Grands Prix between 2016 and 2017.","facts":["First Grand Prix here: 2016 — 2 World Championship GPs held coming into this season.","2 different winners in 2 Grands Prix.","Race lap record on this layout: 1:43.441 — Sebastian Vettel (2017).","1 of 2 races here was won from pole.","Furthest back a winner has started: P10 (Daniel Ricciardo, 2017)."]},"results":[{"pos":"1","driver":"Lewis Hamilton","team":"Mercedes"},{"pos":"2","driver":"Kimi Räikkönen","team":"Ferrari"},{"pos":"3","driver":"Sergio Pérez","team":"Force India"},{"pos":"4","driver":"Sebastian Vettel","team":"Ferrari"},{"pos":"5","driver":"Carlos Sainz Jr.","team":"Renault"},{"pos":"6","driver":"Charles Leclerc","team":"Sauber"},{"pos":"7","driver":"Fernando Alonso","team":"McLaren"},{"pos":"8","driver":"Lance Stroll","team":"Williams"},{"pos":"9","driver":"Stoffel Vandoorne","team":"McLaren"},{"pos":"10","driver":"Brendon Hartley","team":"Toro Rosso"},{"pos":"11","driver":"Marcus Ericsson","team":"Sauber"},{"pos":"12","driver":"Pierre Gasly","team":"Toro Rosso"},{"pos":"13","driver":"Kevin Magnussen","team":"Haas"},{"pos":"14","driver":"Valtteri Bottas","team":"Mercedes","status":"Puncture"},{"pos":"DNF","driver":"Romain Grosjean","team":"Haas","status":"Accident"},{"pos":"DNF","driver":"Max Verstappen","team":"Red Bull","status":"Collision"},{"pos":"DNF","driver":"Daniel Ricciardo","team":"Red Bull","status":"Collision"},{"pos":"DNF","driver":"Nico Hülkenberg","team":"Renault","status":"Accident"},{"pos":"DNF","driver":"Esteban Ocon","team":"Force India","status":"Collision"},{"pos":"DNF","driver":"Sergey Sirotkin","team":"Williams","status":"Collision"}]},{"round":5,"name":"Spanish Grand Prix","winner":"Lewis Hamilton","winnerTeam":"Mercedes","fastestLap":"Daniel Ricciardo","circuit":{"layoutId":"catalunya-4","name":"Catalunya","place":"Montmeló","type":"RACE","direction":"CLOCKWISE","lengthKm":"4.66","turns":16,"history":"The Catalunya circuit (formerly Circuit de Catalunya) in Montmeló hosted 27 F1 World Championship Grands Prix between 1991 and 2017.","facts":["First Grand Prix here: 1991 — 27 World Championship GPs held coming into this season.","Most wins here: Michael Schumacher (6).","Most pole positions: Michael Schumacher (7).","Most successful constructor: Ferrari (8 wins).","16 different winners in 27 Grands Prix.","Race lap record on this layout: 1:21.670 — Kimi Räikkönen (2008)."]},"results":[{"pos":"1","driver":"Lewis Hamilton","team":"Mercedes"},{"pos":"2","driver":"Valtteri Bottas","team":"Mercedes"},{"pos":"3","driver":"Max Verstappen","team":"Red Bull"},{"pos":"4","driver":"Sebastian Vettel","team":"Ferrari"},{"pos":"5","driver":"Daniel Ricciardo","team":"Red Bull"},{"pos":"6","driver":"Kevin Magnussen","team":"Haas"},{"pos":"7","driver":"Carlos Sainz Jr.","team":"Renault"},{"pos":"8","driver":"Fernando Alonso","team":"McLaren"},{"pos":"9","driver":"Sergio Pérez","team":"Force India"},{"pos":"10","driver":"Charles Leclerc","team":"Sauber"},{"pos":"11","driver":"Lance Stroll","team":"Williams"},{"pos":"12","driver":"Brendon Hartley","team":"Toro Rosso"},{"pos":"13","driver":"Marcus Ericsson","team":"Sauber"},{"pos":"14","driver":"Sergey Sirotkin","team":"Williams"},{"pos":"DNF","driver":"Stoffel Vandoorne","team":"McLaren","status":"Gearbox"},{"pos":"DNF","driver":"Esteban Ocon","team":"Force India","status":"Oil leak"},{"pos":"DNF","driver":"Kimi Räikkönen","team":"Ferrari","status":"Turbo"},{"pos":"DNF","driver":"Romain Grosjean","team":"Haas","status":"Collision"},{"pos":"DNF","driver":"Pierre Gasly","team":"Toro Rosso","status":"Collision"},{"pos":"DNF","driver":"Nico Hülkenberg","team":"Renault","status":"Collision"}]},{"round":6,"name":"Monaco Grand Prix","winner":"Daniel Ricciardo","winnerTeam":"Red Bull","fastestLap":"Max Verstappen","circuit":{"layoutId":"monaco-6","name":"Monaco","place":"Monte Carlo","type":"STREET","direction":"CLOCKWISE","lengthKm":"3.34","turns":19,"history":"The Monaco circuit in Monte Carlo hosted 64 F1 World Championship Grands Prix between 1950 and 2017.","facts":["First Grand Prix here: 1950 — 64 World Championship GPs held coming into this season.","Most wins here: Ayrton Senna (6).","Most pole positions: Ayrton Senna (5).","Most successful constructor: McLaren (15 wins).","33 different winners in 64 Grands Prix.","Race lap record on this layout: 1:14.439 — Michael Schumacher (2004)."]},"results":[{"pos":"1","driver":"Daniel Ricciardo","team":"Red Bull"},{"pos":"2","driver":"Sebastian Vettel","team":"Ferrari"},{"pos":"3","driver":"Lewis Hamilton","team":"Mercedes"},{"pos":"4","driver":"Kimi Räikkönen","team":"Ferrari"},{"pos":"5","driver":"Valtteri Bottas","team":"Mercedes"},{"pos":"6","driver":"Esteban Ocon","team":"Force India"},{"pos":"7","driver":"Pierre Gasly","team":"Toro Rosso"},{"pos":"8","driver":"Nico Hülkenberg","team":"Renault"},{"pos":"9","driver":"Max Verstappen","team":"Red Bull"},{"pos":"10","driver":"Carlos Sainz Jr.","team":"Renault"},{"pos":"11","driver":"Marcus Ericsson","team":"Sauber"},{"pos":"12","driver":"Sergio Pérez","team":"Force India"},{"pos":"13","driver":"Kevin Magnussen","team":"Haas"},{"pos":"14","driver":"Stoffel Vandoorne","team":"McLaren"},{"pos":"15","driver":"Romain Grosjean","team":"Haas"},{"pos":"16","driver":"Sergey Sirotkin","team":"Williams"},{"pos":"17","driver":"Lance Stroll","team":"Williams"},{"pos":"18","driver":"Charles Leclerc","team":"Sauber","status":"Collision"},{"pos":"19","driver":"Brendon Hartley","team":"Toro Rosso","status":"Collision damage"},{"pos":"DNF","driver":"Fernando Alonso","team":"McLaren","status":"Gearbox"}]},{"round":7,"name":"Canadian Grand Prix","winner":"Sebastian Vettel","winnerTeam":"Ferrari","fastestLap":"Max Verstappen","circuit":{"layoutId":"montreal-6","name":"Gilles Villeneuve","place":"Montreal","type":"STREET","direction":"CLOCKWISE","lengthKm":"4.36","turns":14,"history":"The Gilles Villeneuve circuit (formerly Île Notre-Dame Circuit) in Montreal hosted 38 F1 World Championship Grands Prix between 1978 and 2017.","facts":["First Grand Prix here: 1978 — 38 World Championship GPs held coming into this season.","Most wins here: Michael Schumacher (7).","Most pole positions: Lewis Hamilton / Michael Schumacher (6 each).","Most successful constructor: Ferrari (10 wins).","23 different winners in 38 Grands Prix.","Race lap record on this layout: 1:13.622 — Rubens Barrichello (2004)."]},"results":[{"pos":"1","driver":"Sebastian Vettel","team":"Ferrari"},{"pos":"2","driver":"Valtteri Bottas","team":"Mercedes"},{"pos":"3","driver":"Max Verstappen","team":"Red Bull"},{"pos":"4","driver":"Daniel Ricciardo","team":"Red Bull"},{"pos":"5","driver":"Lewis Hamilton","team":"Mercedes"},{"pos":"6","driver":"Kimi Räikkönen","team":"Ferrari"},{"pos":"7","driver":"Nico Hülkenberg","team":"Renault"},{"pos":"8","driver":"Carlos Sainz Jr.","team":"Renault"},{"pos":"9","driver":"Esteban Ocon","team":"Force India"},{"pos":"10","driver":"Charles Leclerc","team":"Sauber"},{"pos":"11","driver":"Pierre Gasly","team":"Toro Rosso"},{"pos":"12","driver":"Romain Grosjean","team":"Haas"},{"pos":"13","driver":"Kevin Magnussen","team":"Haas"},{"pos":"14","driver":"Sergio Pérez","team":"Force India"},{"pos":"15","driver":"Marcus Ericsson","team":"Sauber"},{"pos":"16","driver":"Stoffel Vandoorne","team":"McLaren"},{"pos":"17","driver":"Sergey Sirotkin","team":"Williams"},{"pos":"DNF","driver":"Fernando Alonso","team":"McLaren","status":"Exhaust"},{"pos":"DNF","driver":"Brendon Hartley","team":"Toro Rosso","status":"Collision"},{"pos":"DNF","driver":"Lance Stroll","team":"Williams","status":"Collision"}]},{"round":8,"name":"French Grand Prix","winner":"Lewis Hamilton","winnerTeam":"Mercedes","fastestLap":"Valtteri Bottas","circuit":{"layoutId":"paul-ricard-3","name":"Paul Ricard","place":"Le Castellet","type":"RACE","direction":"CLOCKWISE","lengthKm":"5.84","turns":15,"history":"The Paul Ricard circuit in Le Castellet hosted 14 F1 World Championship Grands Prix between 1971 and 1990.","facts":["First Grand Prix here: 1971 — 14 World Championship GPs held coming into this season.","Most wins here: Alain Prost (4).","Most pole positions: Alain Prost (3).","Most successful constructor: McLaren / Williams (3 each).","10 different winners in 14 Grands Prix.","8 of 14 races here were won from pole."]},"results":[{"pos":"1","driver":"Lewis Hamilton","team":"Mercedes"},{"pos":"2","driver":"Max Verstappen","team":"Red Bull"},{"pos":"3","driver":"Kimi Räikkönen","team":"Ferrari"},{"pos":"4","driver":"Daniel Ricciardo","team":"Red Bull"},{"pos":"5","driver":"Sebastian Vettel","team":"Ferrari"},{"pos":"6","driver":"Kevin Magnussen","team":"Haas"},{"pos":"7","driver":"Valtteri Bottas","team":"Mercedes"},{"pos":"8","driver":"Carlos Sainz Jr.","team":"Renault"},{"pos":"9","driver":"Nico Hülkenberg","team":"Renault"},{"pos":"10","driver":"Charles Leclerc","team":"Sauber"},{"pos":"11","driver":"Romain Grosjean","team":"Haas"},{"pos":"12","driver":"Stoffel Vandoorne","team":"McLaren"},{"pos":"13","driver":"Marcus Ericsson","team":"Sauber"},{"pos":"14","driver":"Brendon Hartley","team":"Toro Rosso"},{"pos":"15","driver":"Sergey Sirotkin","team":"Williams"},{"pos":"16","driver":"Fernando Alonso","team":"McLaren","status":"Suspension"},{"pos":"17","driver":"Lance Stroll","team":"Williams","status":"Puncture"},{"pos":"DNF","driver":"Sergio Pérez","team":"Force India","status":"Engine"},{"pos":"DNF","driver":"Esteban Ocon","team":"Force India","status":"Collision"},{"pos":"DNF","driver":"Pierre Gasly","team":"Toro Rosso","status":"Collision"}]},{"round":9,"name":"Austrian Grand Prix","winner":"Max Verstappen","winnerTeam":"Red Bull","fastestLap":"Kimi Räikkönen","circuit":{"layoutId":"spielberg-3","name":"Red Bull Ring","place":"Spielberg","type":"RACE","direction":"CLOCKWISE","lengthKm":"4.33","turns":10,"history":"The Red Bull Ring circuit (formerly Österreichring;A1-Ring) in Spielberg hosted 29 F1 World Championship Grands Prix between 1970 and 2017.","facts":["First Grand Prix here: 1970 — 29 World Championship GPs held coming into this season.","Most wins here: Alain Prost (3).","Most pole positions: Nelson Piquet / Niki Lauda / René Arnoux (3 each).","Most successful constructor: McLaren (6 wins).","22 different winners in 29 Grands Prix.","Race lap record on this layout: 1:07.411 — Lewis Hamilton (2017)."]},"results":[{"pos":"1","driver":"Max Verstappen","team":"Red Bull"},{"pos":"2","driver":"Kimi Räikkönen","team":"Ferrari"},{"pos":"3","driver":"Sebastian Vettel","team":"Ferrari"},{"pos":"4","driver":"Romain Grosjean","team":"Haas"},{"pos":"5","driver":"Kevin Magnussen","team":"Haas"},{"pos":"6","driver":"Esteban Ocon","team":"Force India"},{"pos":"7","driver":"Sergio Pérez","team":"Force India"},{"pos":"8","driver":"Fernando Alonso","team":"McLaren"},{"pos":"9","driver":"Charles Leclerc","team":"Sauber"},{"pos":"10","driver":"Marcus Ericsson","team":"Sauber"},{"pos":"11","driver":"Pierre Gasly","team":"Toro Rosso"},{"pos":"12","driver":"Carlos Sainz Jr.","team":"Renault"},{"pos":"13","driver":"Sergey Sirotkin","team":"Williams"},{"pos":"14","driver":"Lance Stroll","team":"Williams"},{"pos":"15","driver":"Stoffel Vandoorne","team":"McLaren","status":"Collision damage"},{"pos":"DNF","driver":"Lewis Hamilton","team":"Mercedes","status":"Fuel pressure"},{"pos":"DNF","driver":"Brendon Hartley","team":"Toro Rosso","status":"Hydraulics"},{"pos":"DNF","driver":"Daniel Ricciardo","team":"Red Bull","status":"Exhaust"},{"pos":"DNF","driver":"Valtteri Bottas","team":"Mercedes","status":"Hydraulics"},{"pos":"DNF","driver":"Nico Hülkenberg","team":"Renault","status":"Engine"}]},{"round":10,"name":"British Grand Prix","winner":"Sebastian Vettel","winnerTeam":"Ferrari","fastestLap":"Sebastian Vettel","circuit":{"layoutId":"silverstone-8","name":"Silverstone","place":"Silverstone","type":"RACE","direction":"CLOCKWISE","lengthKm":"5.89","turns":18,"history":"The Silverstone circuit hosted 51 F1 World Championship Grands Prix between 1950 and 2017.","facts":["First Grand Prix here: 1950 — 51 World Championship GPs held coming into this season.","Most wins here: Alain Prost / Lewis Hamilton (5 each).","Most pole positions: Lewis Hamilton (5).","Most successful constructor: Ferrari (13 wins).","30 different winners in 51 Grands Prix.","Race lap record on this layout: 1:30.621 — Lewis Hamilton (2017)."]},"results":[{"pos":"1","driver":"Sebastian Vettel","team":"Ferrari"},{"pos":"2","driver":"Lewis Hamilton","team":"Mercedes"},{"pos":"3","driver":"Kimi Räikkönen","team":"Ferrari"},{"pos":"4","driver":"Valtteri Bottas","team":"Mercedes"},{"pos":"5","driver":"Daniel Ricciardo","team":"Red Bull"},{"pos":"6","driver":"Nico Hülkenberg","team":"Renault"},{"pos":"7","driver":"Esteban Ocon","team":"Force India"},{"pos":"8","driver":"Fernando Alonso","team":"McLaren"},{"pos":"9","driver":"Kevin Magnussen","team":"Haas"},{"pos":"10","driver":"Sergio Pérez","team":"Force India"},{"pos":"11","driver":"Stoffel Vandoorne","team":"McLaren"},{"pos":"12","driver":"Lance Stroll","team":"Williams"},{"pos":"13","driver":"Pierre Gasly","team":"Toro Rosso"},{"pos":"14","driver":"Sergey Sirotkin","team":"Williams"},{"pos":"15","driver":"Max Verstappen","team":"Red Bull","status":"Brakes"},{"pos":"DNF","driver":"Romain Grosjean","team":"Haas","status":"Collision"},{"pos":"DNF","driver":"Carlos Sainz Jr.","team":"Renault","status":"Collision"},{"pos":"DNF","driver":"Marcus Ericsson","team":"Sauber","status":"Accident"},{"pos":"DNF","driver":"Charles Leclerc","team":"Sauber","status":"Wheel"},{"pos":"DNF","driver":"Brendon Hartley","team":"Toro Rosso","status":"Power unit"}]},{"round":11,"name":"German Grand Prix","winner":"Lewis Hamilton","winnerTeam":"Mercedes","fastestLap":"Lewis Hamilton","circuit":{"layoutId":"hockenheimring-4","name":"Hockenheimring","place":"Hockenheim","type":"RACE","direction":"CLOCKWISE","lengthKm":"4.57","turns":17,"history":"The Hockenheimring circuit in Hockenheim hosted 35 F1 World Championship Grands Prix between 1970 and 2016.","facts":["First Grand Prix here: 1970 — 35 World Championship GPs held coming into this season.","Most wins here: Michael Schumacher (4).","Most pole positions: Alain Prost / Ayrton Senna / Nigel Mansell (3 each).","Most successful constructor: Ferrari (11 wins).","22 different winners in 35 Grands Prix.","Race lap record on this layout: 1:13.780 — Kimi Räikkönen (2004)."]},"results":[{"pos":"1","driver":"Lewis Hamilton","team":"Mercedes"},{"pos":"2","driver":"Valtteri Bottas","team":"Mercedes"},{"pos":"3","driver":"Kimi Räikkönen","team":"Ferrari"},{"pos":"4","driver":"Max Verstappen","team":"Red Bull"},{"pos":"5","driver":"Nico Hülkenberg","team":"Renault"},{"pos":"6","driver":"Romain Grosjean","team":"Haas"},{"pos":"7","driver":"Sergio Pérez","team":"Force India"},{"pos":"8","driver":"Esteban Ocon","team":"Force India"},{"pos":"9","driver":"Marcus Ericsson","team":"Sauber"},{"pos":"10","driver":"Brendon Hartley","team":"Toro Rosso"},{"pos":"11","driver":"Kevin Magnussen","team":"Haas"},{"pos":"12","driver":"Carlos Sainz Jr.","team":"Renault"},{"pos":"13","driver":"Stoffel Vandoorne","team":"McLaren"},{"pos":"14","driver":"Pierre Gasly","team":"Toro Rosso"},{"pos":"15","driver":"Charles Leclerc","team":"Sauber"},{"pos":"16","driver":"Fernando Alonso","team":"McLaren","status":"Gearbox"},{"pos":"DNF","driver":"Lance Stroll","team":"Williams","status":"Brakes"},{"pos":"DNF","driver":"Sebastian Vettel","team":"Ferrari","status":"Accident"},{"pos":"DNF","driver":"Sergey Sirotkin","team":"Williams","status":"Oil leak"},{"pos":"DNF","driver":"Daniel Ricciardo","team":"Red Bull","status":"Power loss"}]},{"round":12,"name":"Hungarian Grand Prix","winner":"Lewis Hamilton","winnerTeam":"Mercedes","fastestLap":"Daniel Ricciardo","circuit":{"layoutId":"hungaroring-3","name":"Hungaroring","place":"Budapest","type":"RACE","direction":"CLOCKWISE","lengthKm":"4.38","turns":14,"history":"The Hungaroring circuit in Budapest hosted 32 F1 World Championship Grands Prix between 1986 and 2017.","facts":["First Grand Prix here: 1986 — 32 World Championship GPs held coming into this season.","Most wins here: Lewis Hamilton (5).","Most pole positions: Michael Schumacher (7).","Most successful constructor: McLaren (11 wins).","17 different winners in 32 Grands Prix.","Race lap record on this layout: 1:19.071 — Michael Schumacher (2004)."]},"results":[{"pos":"1","driver":"Lewis Hamilton","team":"Mercedes"},{"pos":"2","driver":"Sebastian Vettel","team":"Ferrari"},{"pos":"3","driver":"Kimi Räikkönen","team":"Ferrari"},{"pos":"4","driver":"Daniel Ricciardo","team":"Red Bull"},{"pos":"5","driver":"Valtteri Bottas","team":"Mercedes"},{"pos":"6","driver":"Pierre Gasly","team":"Toro Rosso"},{"pos":"7","driver":"Kevin Magnussen","team":"Haas"},{"pos":"8","driver":"Fernando Alonso","team":"McLaren"},{"pos":"9","driver":"Carlos Sainz Jr.","team":"Renault"},{"pos":"10","driver":"Romain Grosjean","team":"Haas"},{"pos":"11","driver":"Brendon Hartley","team":"Toro Rosso"},{"pos":"12","driver":"Nico Hülkenberg","team":"Renault"},{"pos":"13","driver":"Esteban Ocon","team":"Force India"},{"pos":"14","driver":"Sergio Pérez","team":"Force India"},{"pos":"15","driver":"Marcus Ericsson","team":"Sauber"},{"pos":"16","driver":"Sergey Sirotkin","team":"Williams"},{"pos":"17","driver":"Lance Stroll","team":"Williams"},{"pos":"DNF","driver":"Stoffel Vandoorne","team":"McLaren","status":"Gearbox"},{"pos":"DNF","driver":"Max Verstappen","team":"Red Bull","status":"Power loss"},{"pos":"DNF","driver":"Charles Leclerc","team":"Sauber","status":"Suspension"}]},{"round":13,"name":"Belgian Grand Prix","winner":"Sebastian Vettel","winnerTeam":"Ferrari","fastestLap":"Valtteri Bottas","circuit":{"layoutId":"spa-francorchamps-4","name":"Spa-Francorchamps","place":"Spa","type":"RACE","direction":"CLOCKWISE","lengthKm":"7","turns":19,"history":"The Spa-Francorchamps circuit in Spa hosted 50 F1 World Championship Grands Prix between 1950 and 2017.","facts":["First Grand Prix here: 1950 — 50 World Championship GPs held coming into this season.","Most wins here: Michael Schumacher (6).","Most pole positions: Ayrton Senna / Juan Manuel Fangio / Lewis Hamilton (4 each).","Most successful constructor: Ferrari / McLaren (12 each).","26 different winners in 50 Grands Prix.","Race lap record on this layout: 1:46.577 — Sebastian Vettel (2017)."]},"results":[{"pos":"1","driver":"Sebastian Vettel","team":"Ferrari"},{"pos":"2","driver":"Lewis Hamilton","team":"Mercedes"},{"pos":"3","driver":"Max Verstappen","team":"Red Bull"},{"pos":"4","driver":"Valtteri Bottas","team":"Mercedes"},{"pos":"5","driver":"Sergio Pérez","team":"Force India"},{"pos":"6","driver":"Esteban Ocon","team":"Force India"},{"pos":"7","driver":"Romain Grosjean","team":"Haas"},{"pos":"8","driver":"Kevin Magnussen","team":"Haas"},{"pos":"9","driver":"Pierre Gasly","team":"Toro Rosso"},{"pos":"10","driver":"Marcus Ericsson","team":"Sauber"},{"pos":"11","driver":"Carlos Sainz Jr.","team":"Renault"},{"pos":"12","driver":"Sergey Sirotkin","team":"Williams"},{"pos":"13","driver":"Lance Stroll","team":"Williams"},{"pos":"14","driver":"Brendon Hartley","team":"Toro Rosso"},{"pos":"15","driver":"Stoffel Vandoorne","team":"McLaren"},{"pos":"DNF","driver":"Daniel Ricciardo","team":"Red Bull","status":"Collision damage"},{"pos":"DNF","driver":"Kimi Räikkönen","team":"Ferrari","status":"Collision damage"},{"pos":"DNF","driver":"Charles Leclerc","team":"Sauber","status":"Collision"},{"pos":"DNF","driver":"Fernando Alonso","team":"McLaren","status":"Collision"},{"pos":"DNF","driver":"Nico Hülkenberg","team":"Renault","status":"Collision"}]},{"round":14,"name":"Italian Grand Prix","winner":"Lewis Hamilton","winnerTeam":"Mercedes","fastestLap":"Lewis Hamilton","circuit":{"layoutId":"monza-7","name":"Monza","place":"Monza","type":"RACE","direction":"CLOCKWISE","lengthKm":"5.79","turns":11,"history":"The Monza circuit hosted 67 F1 World Championship Grands Prix between 1950 and 2017.","facts":["First Grand Prix here: 1950 — 67 World Championship GPs held coming into this season.","Most wins here: Michael Schumacher (5).","Most pole positions: Lewis Hamilton (6).","Most successful constructor: Ferrari (18 wins).","36 different winners in 67 Grands Prix.","Race lap record on this layout: 1:21.046 — Rubens Barrichello (2004)."]},"results":[{"pos":"1","driver":"Lewis Hamilton","team":"Mercedes"},{"pos":"2","driver":"Kimi Räikkönen","team":"Ferrari"},{"pos":"3","driver":"Valtteri Bottas","team":"Mercedes"},{"pos":"4","driver":"Sebastian Vettel","team":"Ferrari"},{"pos":"5","driver":"Max Verstappen","team":"Red Bull"},{"pos":"6","driver":"Esteban Ocon","team":"Force India"},{"pos":"7","driver":"Sergio Pérez","team":"Force India"},{"pos":"8","driver":"Carlos Sainz Jr.","team":"Renault"},{"pos":"9","driver":"Lance Stroll","team":"Williams"},{"pos":"10","driver":"Sergey Sirotkin","team":"Williams"},{"pos":"11","driver":"Charles Leclerc","team":"Sauber"},{"pos":"12","driver":"Stoffel Vandoorne","team":"McLaren"},{"pos":"13","driver":"Nico Hülkenberg","team":"Renault"},{"pos":"14","driver":"Pierre Gasly","team":"Toro Rosso"},{"pos":"15","driver":"Marcus Ericsson","team":"Sauber"},{"pos":"16","driver":"Kevin Magnussen","team":"Haas"},{"pos":"DNF","driver":"Daniel Ricciardo","team":"Red Bull","status":"Clutch"},{"pos":"DNF","driver":"Fernando Alonso","team":"McLaren","status":"Electrical"},{"pos":"DNF","driver":"Brendon Hartley","team":"Toro Rosso","status":"Collision"},{"pos":"DSQ","driver":"Romain Grosjean","team":"Haas","status":"Illegal floor"}]},{"round":15,"name":"Singapore Grand Prix","winner":"Lewis Hamilton","winnerTeam":"Mercedes","fastestLap":"Kevin Magnussen","circuit":{"layoutId":"marina-bay-3","name":"Marina Bay","place":"Singapore","type":"STREET","direction":"ANTI_CLOCKWISE","lengthKm":"5.07","turns":23,"history":"The Marina Bay circuit in Singapore hosted 10 F1 World Championship Grands Prix between 2008 and 2017.","facts":["First Grand Prix here: 2008 — 10 World Championship GPs held coming into this season.","Most wins here: Sebastian Vettel (4).","Most pole positions: Sebastian Vettel (4).","Most successful constructor: Mercedes / Red Bull (3 each).","4 different winners in 10 Grands Prix.","Race lap record on this layout: 1:45.008 — Lewis Hamilton (2017)."]},"results":[{"pos":"1","driver":"Lewis Hamilton","team":"Mercedes"},{"pos":"2","driver":"Max Verstappen","team":"Red Bull"},{"pos":"3","driver":"Sebastian Vettel","team":"Ferrari"},{"pos":"4","driver":"Valtteri Bottas","team":"Mercedes"},{"pos":"5","driver":"Kimi Räikkönen","team":"Ferrari"},{"pos":"6","driver":"Daniel Ricciardo","team":"Red Bull"},{"pos":"7","driver":"Fernando Alonso","team":"McLaren"},{"pos":"8","driver":"Carlos Sainz Jr.","team":"Renault"},{"pos":"9","driver":"Charles Leclerc","team":"Sauber"},{"pos":"10","driver":"Nico Hülkenberg","team":"Renault"},{"pos":"11","driver":"Marcus Ericsson","team":"Sauber"},{"pos":"12","driver":"Stoffel Vandoorne","team":"McLaren"},{"pos":"13","driver":"Pierre Gasly","team":"Toro Rosso"},{"pos":"14","driver":"Lance Stroll","team":"Williams"},{"pos":"15","driver":"Romain Grosjean","team":"Haas"},{"pos":"16","driver":"Sergio Pérez","team":"Force India"},{"pos":"17","driver":"Brendon Hartley","team":"Toro Rosso"},{"pos":"18","driver":"Kevin Magnussen","team":"Haas"},{"pos":"19","driver":"Sergey Sirotkin","team":"Williams"},{"pos":"DNF","driver":"Esteban Ocon","team":"Force India","status":"Collision"}]},{"round":16,"name":"Russian Grand Prix","winner":"Lewis Hamilton","winnerTeam":"Mercedes","fastestLap":"Valtteri Bottas","circuit":{"layoutId":"sochi-1","name":"Sochi","place":"Sochi","type":"ROAD","direction":"CLOCKWISE","lengthKm":"5.85","turns":18,"history":"The Sochi circuit (formerly Sochi International Street Circuit;Sochi Olympic Park Circuit) hosted 4 F1 World Championship Grands Prix between 2014 and 2017.","facts":["First Grand Prix here: 2014 — 4 World Championship GPs held coming into this season.","Most wins here: Lewis Hamilton (2).","Most pole positions: Nico Rosberg (2).","Most successful constructor: Mercedes (4 wins).","3 different winners in 4 Grands Prix.","Race lap record on this layout: 1:36.844 — Kimi Räikkönen (2017)."]},"results":[{"pos":"1","driver":"Lewis Hamilton","team":"Mercedes"},{"pos":"2","driver":"Valtteri Bottas","team":"Mercedes"},{"pos":"3","driver":"Sebastian Vettel","team":"Ferrari"},{"pos":"4","driver":"Kimi Räikkönen","team":"Ferrari"},{"pos":"5","driver":"Max Verstappen","team":"Red Bull"},{"pos":"6","driver":"Daniel Ricciardo","team":"Red Bull"},{"pos":"7","driver":"Charles Leclerc","team":"Sauber"},{"pos":"8","driver":"Kevin Magnussen","team":"Haas"},{"pos":"9","driver":"Esteban Ocon","team":"Force India"},{"pos":"10","driver":"Sergio Pérez","team":"Force India"},{"pos":"11","driver":"Romain Grosjean","team":"Haas"},{"pos":"12","driver":"Nico Hülkenberg","team":"Renault"},{"pos":"13","driver":"Marcus Ericsson","team":"Sauber"},{"pos":"14","driver":"Fernando Alonso","team":"McLaren"},{"pos":"15","driver":"Lance Stroll","team":"Williams"},{"pos":"16","driver":"Stoffel Vandoorne","team":"McLaren"},{"pos":"17","driver":"Carlos Sainz Jr.","team":"Renault"},{"pos":"18","driver":"Sergey Sirotkin","team":"Williams"},{"pos":"DNF","driver":"Pierre Gasly","team":"Toro Rosso","status":"Brakes"},{"pos":"DNF","driver":"Brendon Hartley","team":"Toro Rosso","status":"Brakes"}]},{"round":17,"name":"Japanese Grand Prix","winner":"Lewis Hamilton","winnerTeam":"Mercedes","fastestLap":"Sebastian Vettel","circuit":{"layoutId":"suzuka-2","name":"Suzuka","place":"Suzuka","type":"RACE","direction":"CLOCKWISE","lengthKm":"5.81","turns":18,"history":"The Suzuka circuit hosted 29 F1 World Championship Grands Prix between 1987 and 2017.","facts":["First Grand Prix here: 1987 — 29 World Championship GPs held coming into this season.","Most wins here: Michael Schumacher (6).","Most pole positions: Michael Schumacher (8).","Most successful constructor: Ferrari / McLaren (7 each).","15 different winners in 29 Grands Prix.","Race lap record on this layout: 1:31.540 — Kimi Räikkönen (2005)."]},"results":[{"pos":"1","driver":"Lewis Hamilton","team":"Mercedes"},{"pos":"2","driver":"Valtteri Bottas","team":"Mercedes"},{"pos":"3","driver":"Max Verstappen","team":"Red Bull"},{"pos":"4","driver":"Daniel Ricciardo","team":"Red Bull"},{"pos":"5","driver":"Kimi Räikkönen","team":"Ferrari"},{"pos":"6","driver":"Sebastian Vettel","team":"Ferrari"},{"pos":"7","driver":"Sergio Pérez","team":"Force India"},{"pos":"8","driver":"Romain Grosjean","team":"Haas"},{"pos":"9","driver":"Esteban Ocon","team":"Force India"},{"pos":"10","driver":"Carlos Sainz Jr.","team":"Renault"},{"pos":"11","driver":"Pierre Gasly","team":"Toro Rosso"},{"pos":"12","driver":"Marcus Ericsson","team":"Sauber"},{"pos":"13","driver":"Brendon Hartley","team":"Toro Rosso"},{"pos":"14","driver":"Fernando Alonso","team":"McLaren"},{"pos":"15","driver":"Stoffel Vandoorne","team":"McLaren"},{"pos":"16","driver":"Sergey Sirotkin","team":"Williams"},{"pos":"17","driver":"Lance Stroll","team":"Williams"},{"pos":"DNF","driver":"Charles Leclerc","team":"Sauber","status":"Mechanical"},{"pos":"DNF","driver":"Nico Hülkenberg","team":"Renault","status":"Engine"},{"pos":"DNF","driver":"Kevin Magnussen","team":"Haas","status":"Collision damage"}]},{"round":18,"name":"United States Grand Prix","winner":"Kimi Räikkönen","winnerTeam":"Ferrari","fastestLap":"Lewis Hamilton","circuit":{"layoutId":"austin-1","name":"Americas","place":"Austin","type":"RACE","direction":"ANTI_CLOCKWISE","lengthKm":"5.51","turns":20,"history":"The Americas circuit in Austin hosted 6 F1 World Championship Grands Prix between 2012 and 2017.","facts":["First Grand Prix here: 2012 — 6 World Championship GPs held coming into this season.","Most wins here: Lewis Hamilton (5).","Most pole positions: Lewis Hamilton / Nico Rosberg / Sebastian Vettel (2 each).","Most successful constructor: Mercedes (4 wins).","2 different winners in 6 Grands Prix.","Race lap record on this layout: 1:37.766 — Sebastian Vettel (2017)."]},"results":[{"pos":"1","driver":"Kimi Räikkönen","team":"Ferrari"},{"pos":"2","driver":"Max Verstappen","team":"Red Bull"},{"pos":"3","driver":"Lewis Hamilton","team":"Mercedes"},{"pos":"4","driver":"Sebastian Vettel","team":"Ferrari"},{"pos":"5","driver":"Valtteri Bottas","team":"Mercedes"},{"pos":"6","driver":"Nico Hülkenberg","team":"Renault"},{"pos":"7","driver":"Carlos Sainz Jr.","team":"Renault"},{"pos":"8","driver":"Sergio Pérez","team":"Force India"},{"pos":"9","driver":"Brendon Hartley","team":"Toro Rosso"},{"pos":"10","driver":"Marcus Ericsson","team":"Sauber"},{"pos":"11","driver":"Stoffel Vandoorne","team":"McLaren"},{"pos":"12","driver":"Pierre Gasly","team":"Toro Rosso"},{"pos":"13","driver":"Sergey Sirotkin","team":"Williams"},{"pos":"14","driver":"Lance Stroll","team":"Williams"},{"pos":"DNF","driver":"Charles Leclerc","team":"Sauber","status":"Collision damage"},{"pos":"DNF","driver":"Daniel Ricciardo","team":"Red Bull","status":"Battery"},{"pos":"DNF","driver":"Romain Grosjean","team":"Haas","status":"Collision"},{"pos":"DNF","driver":"Fernando Alonso","team":"McLaren","status":"Collision"},{"pos":"DSQ","driver":"Esteban Ocon","team":"Force India","status":"Fuel"},{"pos":"DSQ","driver":"Kevin Magnussen","team":"Haas","status":"Fuel"}]},{"round":19,"name":"Mexican Grand Prix","winner":"Max Verstappen","winnerTeam":"Red Bull","fastestLap":"Valtteri Bottas","circuit":{"layoutId":"mexico-city-3","name":"Hermanos Rodríguez","place":"Mexico City","type":"RACE","direction":"CLOCKWISE","lengthKm":"4.3","turns":17,"history":"The Hermanos Rodríguez circuit (formerly Autódromo Ricardo Rodríguez) in Mexico City hosted 18 F1 World Championship Grands Prix between 1963 and 2017.","facts":["First Grand Prix here: 1963 — 18 World Championship GPs held coming into this season.","Most wins here: Alain Prost / Jim Clark / Nigel Mansell (2 each).","Most pole positions: Jim Clark (4).","Most successful constructor: Lotus / McLaren / Williams (3 each).","15 different winners in 18 Grands Prix.","Race lap record on this layout: 1:18.785 — Sebastian Vettel (2017)."]},"results":[{"pos":"1","driver":"Max Verstappen","team":"Red Bull"},{"pos":"2","driver":"Sebastian Vettel","team":"Ferrari"},{"pos":"3","driver":"Kimi Räikkönen","team":"Ferrari"},{"pos":"4","driver":"Lewis Hamilton","team":"Mercedes"},{"pos":"5","driver":"Valtteri Bottas","team":"Mercedes"},{"pos":"6","driver":"Nico Hülkenberg","team":"Renault"},{"pos":"7","driver":"Charles Leclerc","team":"Sauber"},{"pos":"8","driver":"Stoffel Vandoorne","team":"McLaren"},{"pos":"9","driver":"Marcus Ericsson","team":"Sauber"},{"pos":"10","driver":"Pierre Gasly","team":"Toro Rosso"},{"pos":"11","driver":"Esteban Ocon","team":"Force India"},{"pos":"12","driver":"Lance Stroll","team":"Williams"},{"pos":"13","driver":"Sergey Sirotkin","team":"Williams"},{"pos":"14","driver":"Brendon Hartley","team":"Toro Rosso"},{"pos":"15","driver":"Kevin Magnussen","team":"Haas"},{"pos":"16","driver":"Romain Grosjean","team":"Haas"},{"pos":"DNF","driver":"Daniel Ricciardo","team":"Red Bull","status":"Hydraulics"},{"pos":"DNF","driver":"Sergio Pérez","team":"Force India","status":"Brakes"},{"pos":"DNF","driver":"Carlos Sainz Jr.","team":"Renault","status":"Clutch"},{"pos":"DNF","driver":"Fernando Alonso","team":"McLaren","status":"Water pressure"}]},{"round":20,"name":"Brazilian Grand Prix","winner":"Lewis Hamilton","winnerTeam":"Mercedes","fastestLap":"Valtteri Bottas","circuit":{"layoutId":"interlagos-2","name":"José Carlos Pace","place":"São Paulo","type":"RACE","direction":"ANTI_CLOCKWISE","lengthKm":"4.31","turns":15,"history":"The José Carlos Pace circuit (formerly Interlagos) in São Paulo hosted 35 F1 World Championship Grands Prix between 1973 and 2017.","facts":["First Grand Prix here: 1973 — 35 World Championship GPs held coming into this season.","Most wins here: Michael Schumacher (4).","Most pole positions: Ayrton Senna / Felipe Massa / Mika Häkkinen / Rubens Barrichello (3 each).","Most successful constructor: Ferrari (9 wins).","23 different winners in 35 Grands Prix.","Race lap record on this layout: 1:11.044 — Max Verstappen (2017)."]},"results":[{"pos":"1","driver":"Lewis Hamilton","team":"Mercedes"},{"pos":"2","driver":"Max Verstappen","team":"Red Bull"},{"pos":"3","driver":"Kimi Räikkönen","team":"Ferrari"},{"pos":"4","driver":"Daniel Ricciardo","team":"Red Bull"},{"pos":"5","driver":"Valtteri Bottas","team":"Mercedes"},{"pos":"6","driver":"Sebastian Vettel","team":"Ferrari"},{"pos":"7","driver":"Charles Leclerc","team":"Sauber"},{"pos":"8","driver":"Romain Grosjean","team":"Haas"},{"pos":"9","driver":"Kevin Magnussen","team":"Haas"},{"pos":"10","driver":"Sergio Pérez","team":"Force India"},{"pos":"11","driver":"Brendon Hartley","team":"Toro Rosso"},{"pos":"12","driver":"Carlos Sainz Jr.","team":"Renault"},{"pos":"13","driver":"Pierre Gasly","team":"Toro Rosso"},{"pos":"14","driver":"Esteban Ocon","team":"Force India"},{"pos":"15","driver":"Stoffel Vandoorne","team":"McLaren"},{"pos":"16","driver":"Sergey Sirotkin","team":"Williams"},{"pos":"17","driver":"Fernando Alonso","team":"McLaren"},{"pos":"18","driver":"Lance Stroll","team":"Williams"},{"pos":"DNF","driver":"Nico Hülkenberg","team":"Renault","status":"Overheating"},{"pos":"DNF","driver":"Marcus Ericsson","team":"Sauber","status":"Collision damage"}]},{"round":21,"name":"Abu Dhabi Grand Prix","winner":"Lewis Hamilton","winnerTeam":"Mercedes","fastestLap":"Sebastian Vettel","circuit":{"layoutId":"yas-marina-1","name":"Yas Marina","place":"Abu Dhabi","type":"RACE","direction":"ANTI_CLOCKWISE","lengthKm":"5.55","turns":21,"history":"The Yas Marina circuit in Abu Dhabi hosted 9 F1 World Championship Grands Prix between 2009 and 2017.","facts":["First Grand Prix here: 2009 — 9 World Championship GPs held coming into this season.","Most wins here: Lewis Hamilton / Sebastian Vettel (3 each).","Most pole positions: Lewis Hamilton (3).","Most successful constructor: Mercedes (4 wins).","5 different winners in 9 Grands Prix.","Race lap record on this layout: 1:40.279 — Sebastian Vettel (2009)."]},"results":[{"pos":"1","driver":"Lewis Hamilton","team":"Mercedes"},{"pos":"2","driver":"Sebastian Vettel","team":"Ferrari"},{"pos":"3","driver":"Max Verstappen","team":"Red Bull"},{"pos":"4","driver":"Daniel Ricciardo","team":"Red Bull"},{"pos":"5","driver":"Valtteri Bottas","team":"Mercedes"},{"pos":"6","driver":"Carlos Sainz Jr.","team":"Renault"},{"pos":"7","driver":"Charles Leclerc","team":"Sauber"},{"pos":"8","driver":"Sergio Pérez","team":"Force India"},{"pos":"9","driver":"Romain Grosjean","team":"Haas"},{"pos":"10","driver":"Kevin Magnussen","team":"Haas"},{"pos":"11","driver":"Fernando Alonso","team":"McLaren"},{"pos":"12","driver":"Brendon Hartley","team":"Toro Rosso"},{"pos":"13","driver":"Lance Stroll","team":"Williams"},{"pos":"14","driver":"Stoffel Vandoorne","team":"McLaren"},{"pos":"15","driver":"Sergey Sirotkin","team":"Williams"},{"pos":"DNF","driver":"Pierre Gasly","team":"Toro Rosso","status":"Engine"},{"pos":"DNF","driver":"Esteban Ocon","team":"Force India","status":"Engine"},{"pos":"DNF","driver":"Marcus Ericsson","team":"Sauber","status":"Power loss"},{"pos":"DNF","driver":"Kimi Räikkönen","team":"Ferrari","status":"Power loss"},{"pos":"DNF","driver":"Nico Hülkenberg","team":"Renault","status":"Collision"}]}]}