{
  "entries": [
    {
      "teamId": "team.mclaren",
      "driverId": "driver.ayrton_senna",
      "number": "1",
      "rounds": "1-16",
      "ams2LiveryName": "McLaren-Honda #1 A. Senna"
    },
    {
      "teamId": "team.mclaren",
      "driverId": "driver.gerhard_berger",
      "number": "2",
      "rounds": "1-16",
      "ams2LiveryName": "McLaren-Honda #2 G. Berger"
    },
    {
      "teamId": "team.tyrrell",
      "driverId": "driver.olivier_grouillard",
      "number": "3",
      "rounds": "1-16",
      "ams2LiveryName": "Tyrrell-Ilmor #3 O. Grouillard"
    },
    {
      "teamId": "team.tyrrell",
      "driverId": "driver.andrea_de_cesaris",
      "number": "4",
      "rounds": "1-16",
      "ams2LiveryName": "Tyrrell-Ilmor #4 A. de Cesaris"
    },
    {
      "teamId": "team.williams",
      "driverId": "driver.nigel_mansell",
      "number": "5",
      "rounds": "1-16",
      "ams2LiveryName": "Williams-Renault #5 N. Mansell"
    },
    {
      "teamId": "team.williams",
      "driverId": "driver.riccardo_patrese",
      "number": "6",
      "rounds": "1-16",
      "ams2LiveryName": "Williams-Renault #6 R. Patrese"
    },
    {
      "teamId": "team.brabham",
      "driverId": "driver.eric_van_de_poele",
      "number": "7",
      "rounds": "1-16",
      "ams2LiveryName": "Brabham-Judd #7 E. van de Poele"
    },
    {
      "teamId": "team.brabham",
      "driverId": "driver.giovanna_amati",
      "number": "8",
      "rounds": "1-16",
      "ams2LiveryName": "Brabham-Judd #8 G. Amati"
    },
    {
      "teamId": "team.footwork",
      "driverId": "driver.michele_alboreto",
      "number": "9",
      "rounds": "1-16",
      "ams2LiveryName": "Footwork-Mugen #9 M. Alboreto"
    },
    {
      "teamId": "team.footwork",
      "driverId": "driver.aguri_suzuki",
      "number": "10",
      "rounds": "1-16",
      "ams2LiveryName": "Footwork-Mugen #10 A. Suzuki"
    },
    {
      "teamId": "team.lotus",
      "driverId": "driver.mika_hakkinen",
      "number": "11",
      "rounds": "1-16",
      "ams2LiveryName": "Lotus-Ford #11 M. H\u00E4kkinen"
    },
    {
      "teamId": "team.lotus",
      "driverId": "driver.johnny_herbert",
      "number": "12",
      "rounds": "1-16",
      "ams2LiveryName": "Lotus-Ford #12 J. Herbert"
    },
    {
      "teamId": "team.fondmetal",
      "driverId": "driver.andrea_chiesa",
      "number": "14",
      "rounds": "1-16",
      "ams2LiveryName": "Fondmetal-Ford #14 A. Chiesa"
    },
    {
      "teamId": "team.fondmetal",
      "driverId": "driver.gabriele_tarquini",
      "number": "15",
      "rounds": "1-16",
      "ams2LiveryName": "Fondmetal-Ford #15 G. Tarquini"
    },
    {
      "teamId": "team.march",
      "driverId": "driver.karl_wendlinger",
      "number": "16",
      "rounds": "1-16",
      "ams2LiveryName": "March-Ilmor #16 K. Wendlinger"
    },
    {
      "teamId": "team.march",
      "driverId": "driver.paul_belmondo",
      "number": "17",
      "rounds": "1-16",
      "ams2LiveryName": "March-Ilmor #17 P. Belmondo"
    },
    {
      "teamId": "team.benetton",
      "driverId": "driver.michael_schumacher",
      "number": "19",
      "rounds": "1-16",
      "ams2LiveryName": "Benetton-Ford #19 M. Schumacher"
    },
    {
      "teamId": "team.benetton",
      "driverId": "driver.martin_brundle",
      "number": "20",
      "rounds": "1-16",
      "ams2LiveryName": "Benetton-Ford #20 M. Brundle"
    },
    {
      "teamId": "team.dallara",
      "driverId": "driver.jj_lehto",
      "number": "21",
      "rounds": "1-16",
      "ams2LiveryName": "Dallara-Ferrari #21 J.J. Lehto"
    },
    {
      "teamId": "team.dallara",
      "driverId": "driver.pierluigi_martini",
      "number": "22",
      "rounds": "1-16",
      "ams2LiveryName": "Dallara-Ferrari #22 P. Martini"
    },
    {
      "teamId": "team.minardi",
      "driverId": "driver.christian_fittipaldi",
      "number": "23",
      "rounds": "1-16",
      "ams2LiveryName": "Minardi-Lamborghini #23 C. Fittipaldi"
    },
    {
      "teamId": "team.minardi",
      "driverId": "driver.gianni_morbidelli",
      "number": "24",
      "rounds": "1-16",
      "ams2LiveryName": "Minardi-Lamborghini #24 G. Morbidelli"
    },
    {
      "teamId": "team.ligier",
      "driverId": "driver.thierry_boutsen",
      "number": "25",
      "rounds": "1-16",
      "ams2LiveryName": "Ligier-Renault #25 T. Boutsen"
    },
    {
      "teamId": "team.ligier",
      "driverId": "driver.erik_comas",
      "number": "26",
      "rounds": "1-16",
      "ams2LiveryName": "Ligier-Renault #26 E. Comas"
    },
    {
      "teamId": "team.ferrari",
      "driverId": "driver.jean_alesi",
      "number": "27",
      "rounds": "1-16",
      "ams2LiveryName": "Scuderia Ferrari #27 J. Alesi"
    },
    {
      "teamId": "team.ferrari",
      "driverId": "driver.ivan_capelli",
      "number": "28",
      "rounds": "1-16",
      "ams2LiveryName": "Scuderia Ferrari #28 I. Capelli"
    },
    {
      "teamId": "team.venturi",
      "driverId": "driver.bertrand_gachot",
      "number": "29",
      "rounds": "1-16",
      "ams2LiveryName": "Larrousse-Lamborghini #29 B. Gachot"
    },
    {
      "teamId": "team.venturi",
      "driverId": "driver.ukyo_katayama",
      "number": "30",
      "rounds": "1-16",
      "ams2LiveryName": "Larrousse-Lamborghini #30 U. Katayama"
    },
    {
      "teamId": "team.jordan",
      "driverId": "driver.stefano_modena",
      "number": "32",
      "rounds": "1-16",
      "ams2LiveryName": "Jordan-Yamaha #32 S.Modena"
    },
    {
      "teamId": "team.jordan",
      "driverId": "driver.mauricio_gugelmin",
      "number": "33",
      "rounds": "1-16",
      "ams2LiveryName": "Jordan-Yamaha #33 M. Gugelmin"
    },
    {
      "teamId": "team.andrea_moda",
      "driverId": "driver.alex_caffi",
      "number": "34",
      "rounds": "1-16",
      "ams2LiveryName": "Andrea Moda-Judd #34 A. Caffi"
    },
    {
      "teamId": "team.andrea_moda",
      "driverId": "driver.enrico_bertaggia",
      "number": "35",
      "rounds": "1-16",
      "ams2LiveryName": "Andrea Moda-Judd #35 E. Bertaggia"
    }
  ]
}